gclone/__init__.py
gclone/__main__.py
gclone/gclone.py
gclone-1.0.3.dist-info/DESCRIPTION.rst
gclone-1.0.3.dist-info/METADATA
gclone-1.0.3.dist-info/RECORD
gclone-1.0.3.dist-info/WHEEL
gclone-1.0.3.dist-info/entry_points.txt
gclone-1.0.3.dist-info/metadata.json
gclone-1.0.3.dist-info/top_level.txt
