Metadata-Version: 2.0
Name: gclone
Version: 1.0.3
Summary: Clone github repositories by name or keyword.
Home-page: https://github.com/mtbrock/gclone
Author: Matthew Brock
Author-email: mtbrock1@gmail.com
License: UNKNOWN
Keywords: git clone gclone pygithub
Platform: UNKNOWN
Classifier: Development Status :: 3 - Alpha
Classifier: Intended Audience :: Developers
Classifier: Topic :: Software Development :: Build Tools
Classifier: License :: OSI Approved :: MIT License
Classifier: Programming Language :: Python :: 3
Classifier: Programming Language :: Python :: 3.4
Classifier: Programming Language :: Python :: 3.5
Classifier: Programming Language :: Python :: 3.6
Requires-Dist: pygithub
